{
  "id": "blog-15-expert-tips-movers-addis",
  "title": "15 Expert Tips from Professional Movers in Addis Ababa",
  "titleAm": "",
  "excerpt": "Fifteen field-tested tips: identical bidder briefs, box discipline, labeling, elevator buffers, door security, valuables, photos, crew communication, and sign-off discipline.",
  "excerptAm": "",
  "content": "<h2>Fifteen expert tips from professional movers in Addis Ababa</h2><p>These tips come from how trained crews actually work on site—not from generic articles. Use them to reduce damage, cut surprise charges, and keep your move day predictable.</p><h3>Tip 1: One identical brief for every company</h3><p>Same PDF to three bidders: addresses, floors, elevator rules, parking photo, box estimate, bulky list. Apples-to-apples quotes reveal who estimated honestly.</p><h3>Tip 2: Measure the worst turn before quote day</h3><p>King mattresses and wall units fail at landings, not in living rooms. Measure clear width and height on the tightest stair or elevator opening.</p><h3>Tip 3: Small boxes for heavy things</h3><p>Books, tools, and dishes belong in small cartons. Large heavy boxes crush, injure crews, and slow everyone down.</p><h3>Tip 4: Double-tape every bottom</h3><p>One strip is a spill waiting to happen. Pros tape in an H pattern.</p><h3>Tip 5: Label two sides plus top</h3><p>Crews stack vertically; one labeled side hides. Room name plus fragile in large letters.</p><h3>Tip 6: Open First box is sacred</h3><p>Coffee, mugs, chargers, toilet paper, wipes, meds, basic tools—not mixed into random kitchen cartons.</p><h3>Tip 7: Elevator buffer time</h3><p>Book ten extra minutes. Finishing early beats fighting the next reservation mid-sofa.</p><h3>Tip 8: Door monitor when doors stay open</h3><p>Propped doors are theft windows. Rotate a household member or ask the lead for a watch rotation.</p><h3>Tip 9: Valuables off the truck</h3><p>Cash, jewelry, passports, and original deeds travel with a person.</p><h3>Tip 10: Photos before wrap</h3><p>Serial numbers on electronics and existing scratches on wood—baseline for any claim conversation.</p><h3>Tip 11: Disassembly only if your contract says so</h3><p>Stripped screws from owner prep cost time. When unsure, let the crew lead decide.</p><h3>Tip 12: Hydration and shade for crews</h3><p>Fed crews pace better. Respect break times—tired people drop things.</p><h3>Tip 13: One adult speaks to the lead</h3><p>Conflicting instructions from three relatives create chaos and billable confusion.</p><h3>Tip 14: Final room sweep ritual</h3><p>Closets, balconies, storage cages—before lockup. Pros find forgotten items daily.</p><h3>Tip 15: Sign completion only after walkthrough</h3><p>Note visible issues on the paperwork. Late claims without same-day notice weaken everyone.</p><h2>Bonus: what pros wish you did the night before</h2><ul><li>Defrost fridge if it moves; wipe dry per manual.</li><li>Strip beds except one linen set.</li><li>Charge phones; pack power strips in personal bags.</li></ul><h2>Addis-specific: traffic and building rules</h2><p>Confirm loading hours with management; traffic peaks differ by neighborhood. Share gate pass spelling exactly as on IDs.</p><h2>When tips conflict with your contract</h2><p>Follow your written agreement on disassembly and owner-packed liability. Tips supplement, not override, the contract.</p><h2>Conclusion</h2><p>Professional movers in Addis Ababa perform best when clients prepare like professionals: clear scope, strong boxes, labeled rooms, and calm communication. These fifteen tips are the shortest path there.</p>",
  "contentAm": "",
  "author": "Active Movers Team",
  "category": "moving-tips",
  "tags": [
    "Addis Ababa",
    "moving tips",
    "professional movers",
    "expert advice",
    "relocation",
    "checklist"
  ],
  "tagsAm": [],
  "readTime": 38,
  "featuredImage": "https://www.activemoverset.com/images/gallary/qua28.jpeg",
  "images": [
    "https://www.activemoverset.com/images/gallary/qua29.jpeg",
    "https://www.activemoverset.com/images/gallary/qua30.jpeg"
  ],
  "status": "published",
  "publishedAt": "2026-03-18T09:00:00.000Z",
  "slug": "15-expert-tips-professional-movers-addis-ababa"
}