{
  "id": "blog-office-relocations-efficient",
  "title": "How Movers Handle Office Relocations Efficiently",
  "titleAm": "",
  "excerpt": "Office moves: floor plans, IT and cables, confidential files, modular furniture, phased weekends, unload priority, lessors, validation.",
  "excerptAm": "",
  "content": "<h2>How movers handle office relocations efficiently</h2><p>Efficiency means less downtime: sequenced packing, labeled destinations, IT-aware ordering, and after-hours windows when needed. Movers align physical transport with how your business actually restarts.</p><h2>Discovery and floor plans</h2><p>Numbered desks, cabinets, and shared stations mapped to the new layout. Movers and IT share one labeling scheme.</p><h2>IT and cabling discipline</h2><p>Photo cable runs before disconnect. Pack servers and network gear in original or double-boxed foam. Plan what powers up first at destination.</p><h2>Confidential materials</h2><p>Sealed bins for sensitive files; chain-of-custody if policy requires; shred what does not travel.</p><h2>Modular furniture</h2><p>Disassemble per manufacturer guidance; bag hardware labeled by cluster. Empty pedestals or lock them with keys taped inside manager kits.</p><h2>Phased or weekend moves</h2><p>Split departments across nights if a single cutover is impossible. Book elevators and loading docks for those slots in writing.</p><h2>Priority unload order</h2><p>Network core and reception desks before décor. Helpdesk announcements match the sequence.</p><h2>Insurance and lessor rules</h2><p>Notify landlords for large copiers or racks; confirm liability on leased equipment.</p><h2>Post-move validation</h2><ul><li>Power and ping tests on sample desks.</li><li>Chair and monitor spot checks.</li><li>Feedback loop to facilities for missing labels.</li></ul><h2>Signage and wayfinding</h2><p>Temporary floor arrows and wing labels cut Monday confusion—movers can place boxes; facilities prints maps.</p><h2>Break rooms and kitchens</h2><p>Appliances drained; labeled staff fridges; disposable cups on day one if dishwasher is still in a box.</p><h2>Conclusion</h2><p>Efficient office relocations merge logistics with information flow. When movers, IT, and facilities share one plan, Monday morning looks boring—and that is the goal.</p>",
  "contentAm": "",
  "author": "Active Movers Team",
  "category": "moving-tips",
  "tags": [
    "Addis Ababa",
    "office move",
    "business relocation",
    "IT moving",
    "efficiency",
    "professional movers"
  ],
  "tagsAm": [],
  "readTime": 41,
  "featuredImage": "https://www.activemoverset.com/images/gallary/qua25.jpeg",
  "images": [
    "https://www.activemoverset.com/images/gallary/qua26.jpeg",
    "https://www.activemoverset.com/images/gallary/qua27.jpeg"
  ],
  "status": "published",
  "publishedAt": "2026-06-13T10:30:00.000Z",
  "slug": "how-movers-handle-office-relocations-efficiently"
}