{
  "id": "blog-label-boxes-fork-knife-precision",
  "title": "How to Label Boxes So Your Unpacking Crew Knows Exactly Where Every Single Fork and Knife Goes",
  "titleAm": "",
  "excerpt": "Precision box labeling: kitchen utensils fork knife mapping, unpacking crew instructions, detailed moving labels, kitchen organization move day Addis.",
  "excerptAm": "",
  "content": "<h2>How to label boxes so your unpacking crew knows exactly where every single fork and knife goes</h2>\n<p>Generic \"kitchen\" label dumps fifty cartons on counter—forks in pantry box, knives in bathroom hallucination. Precision labeling maps micro-destination: drawer, zone, and sequence so unpacking crew—or tired you Sunday night—places every fork without archaeological dig through paprika dust.</p>\n<p>This guide labels boxes for utensil-level unpacking precision.</p>\n\n<h2>Label hierarchy system</h2>\n<ul>\n<li><strong>Level 1 — Room color tape:</strong> Blue kitchen.</li>\n<li><strong>Level 2 — Zone code:</strong> K-UTENSILS, K-PANTRY, K-FRAGILE.</li>\n<li><strong>Level 3 — Drawer map:</strong> K-UTENSILS-DRAWER2-Forks.</li>\n<li><strong>Level 4 — Box sequence:</strong> K-UTENSILS-DRAWER2-Forks-01 of 02.</li>\n</ul>\n\n<h2>Kitchen drawer pre-plan</h2>\n<p>Sketch drawer layout new kitchen—number drawers. Pack by drawer not by random counter sweep. Same drawer contents one or two boxes max—label matches sketch.</p>\n\n<h2>Utensil separation</h2>\n<p>Forks knives spoons separated small boxes or zip bags inside labeled carton—crew opens to correct drawer without sort. Sharp knives wrapped; mark SHARP—safety and speed.</p>\n\n<h2>Unpacking crew brief sheet</h2>\n<p>One-page PDF taped inside truck door: color legend, drawer map photo, OPEN FIRST list. WhatsApp photo to crew lead morning of.</p>\n\n<h2>Directional and handling marks</h2>\n<p>THIS SIDE UP; FRAGILE; HEAVY—redundant with precision label reduces mistake.</p>\n\n<h2>Digital backup</h2>\n<p>Spreadsheet row per box contents—filter K-UTENSILS-DRAWER2 finds fork box if label smudged.</p>\n\n<h2>Partial kitchen functional goal</h2>\n<p>Mark K-ESSENTIAL-NIGHT1—one pot, four forks, four plates, kettle—eat before full unpack marathon.</p>\n\n<h2>Active Movers labeling service</h2><p>Request micro-zone labeling at full-service pack—drawer map client supplies.</p>\n\n<h2>Conclusion</h2>\n<p>Label boxes with color, zone, drawer, and sequence—unpacking crew places every fork and knife where sketch dictates, not where chaos lands.</p>",
  "contentAm": "",
  "author": "Active Movers Team",
  "category": "packing-guide",
  "tags": ["labeling", "unpacking", "kitchen", "utensils", "organization", "moving tips"],
  "tagsAm": [],
  "readTime": 55,
  "featuredImage": "https://www.activemoverset.com/images/gallary/qua565.jpeg",
  "images": ["https://www.activemoverset.com/images/gallary/qua566.jpeg", "https://www.activemoverset.com/images/gallary/qua567.jpeg"],
  "status": "published",
  "publishedAt": "2026-11-02T09:00:00.000Z",
  "slug": "label-boxes-unpacking-crew-fork-knife-precision"
}
