{
  "id": "blog-bole-smart-city-corridor-high-rises",
  "title": "Moving to the Rebuilt Bole Smart City Corridor: High-Rises, Underground Power Grids, and Luxury Logistics",
  "titleAm": "",
  "excerpt": "Bole Smart City corridor relocation: high-rise moves, underground power grids, luxury logistics, modern boulevard access, premium tower moving Addis Ababa.",
  "excerptAm": "",
  "content": "<h2>Moving to the rebuilt Bole Smart City corridor: high-rises, underground power grids, and luxury logistics</h2>\n<p>The rebuilt Bole Smart City corridor stacks glass towers, buried utilities, and management regimes stricter than old Bole memory. Moving here is luxury logistics: freight elevators booked to the minute, underground power awareness, and crews who treat marble lobby as client equal to penthouse sofa.</p>\n<p>This guide relocates households and offices into Bole Smart City corridor developments.</p>\n\n<h2>Smart corridor characteristics</h2>\n<ul>\n<li>Multi-lane boulevards with pedestrian priority zones—truck staging off main spine.</li>\n<li>Underground power and telecom—surface poles fewer but access vaults marked.</li>\n<li>Tower clusters sharing freight elevator queues.</li>\n<li>Building apps for visitor and move permits digital.</li>\n<li>Dust and construction overlap phases—route changes monthly.</li>\n</ul>\n\n<h2>High-rise move protocol</h2>\n<p>Freight slot deposit; floor protection spec; COI naming building; crew badge photos pre-submit. Penthouse diagonal furniture survey before contract—hoist contingency priced. Zero-scratch lobby policy—shoe covers runners mandatory.</p>\n\n<h2>Underground grid coordination</h2>\n<p>Confirm unit power live before elevator book wasted; report vault cover damage immediately—never park tailgate on marked access plate. Generator backup rules tower-specific during grid maintenance windows.</p>\n\n<h2>Traffic and staging</h2>\n<p>Basement loading bay timed; overflow legal pocket shuttle; neon avenue evening pedestrian surge avoid unload. Tuesday 7 a.m. load bias corridor-wide.</p>\n\n<h2>Active Movers Bole Smart City tier</h2><p>Luxury protection materials standard; management liaison template; smart corridor route leads assigned.</p>\n\n<h2>Conclusion</h2>\n<p>Bole Smart City corridor moves marry tower compliance, underground utility awareness, and luxury protection—high-rise logistics succeed when smart infrastructure respected as move participant not background.</p>",
  "contentAm": "",
  "author": "Active Movers Team",
  "category": "moving-tips",
  "tags": ["Bole Smart City", "high-rise", "underground power", "luxury logistics", "corridor", "Addis Ababa"],
  "tagsAm": [],
  "readTime": 58,
  "featuredImage": "https://www.activemoverset.com/images/gallary/qua811.jpeg",
  "images": ["https://www.activemoverset.com/images/gallary/qua812.jpeg", "https://www.activemoverset.com/images/gallary/qua813.jpeg"],
  "status": "published",
  "publishedAt": "2027-03-14T09:00:00.000Z",
  "slug": "moving-bole-smart-city-corridor-high-rises-underground-power"
}
