{
  "id": "blog-check-dams-botanical-gardens-outdoor-moisture",
  "title": "Moving Near the New Check Dams and Botanical Gardens: Keeping Your Outdoor Assets Moisture-Free",
  "titleAm": "",
  "excerpt": "Check dams botanical gardens moving: outdoor assets moisture-free, humidity protection, garden furniture relocation near water features Addis eco-projects.",
  "excerptAm": "",
  "content": "<h2>Moving near the new check dams and botanical gardens: keeping your outdoor assets moisture-free</h2>\n<p>Check dams and botanical gardens raise local humidity microclimate—metal rust accelerates, wicker swells, cushion mold whispers. Moving near water-feature developments requires outdoor asset moisture discipline from pack through first dry week new garden.</p>\n<p>This guide keeps outdoor assets moisture-free relocating near check dam and botanical garden zones.</p>\n\n<h2>Outdoor asset categories at risk</h2>\n<ul>\n<li>Metal patio furniture and grill—rust.</li>\n<li>Wicker and wood Adirondack—swell crack cycle.</li>\n<li>Cushion fabrics—mold if stored wet sealed.</li>\n<li>Power tools garden shed—corrosion electrical.</li>\n<li>Children outdoor play wood—rot if damp storage.</li></ul>\n\n<h2>Packing moisture discipline</h2>\n<p>Clean dry completely before wrap; silica gel cushions bag breathable not vinyl trap; disassemble umbrella dry ribs; grill grease removed moisture accelerant; cover furniture transit water-resistant not sealed wet.</p>\n\n<h2>Truck placement</h2>\n<p>Away leaking roof corner; unload prompt not overnight rain truck if forecast—climate bag contingency.</p>\n\n<h2>Destination storage</h2>\n<p>Shed ventilation; elevate off concrete slab pallets; dehumidifier first month lakeside adjacency; rust inhibitor metal touch-up pre-season.</p>\n\n<h2>Landscaping move</h2>\n<p>Pots sealed drainage holes tape transit; soil spill truck prohibited messy—bag tops.</p>\n\n<h2>Active Movers outdoor tier</h2><p>Moisture wrap upgrade; garden asset inventory survey.</p>\n\n<h2>Conclusion</h2>\n<p>Near check dams and botanical gardens move outdoor assets dry-packed, ventilated stored, elevated placed—moisture-free survival when humidity geography acknowledged not ignored after pretty view lease sign.</p>",
  "contentAm": "",
  "author": "Active Movers Team",
  "category": "packing-guide",
  "tags": ["check dams", "botanical gardens", "outdoor furniture", "moisture", "garden assets", "relocation"],
  "tagsAm": [],
  "readTime": 54,
  "featuredImage": "https://www.activemoverset.com/images/gallary/qua802.jpeg",
  "images": ["https://www.activemoverset.com/images/gallary/qua803.jpeg", "https://www.activemoverset.com/images/gallary/qua804.jpeg"],
  "status": "published",
  "publishedAt": "2027-03-11T09:00:00.000Z",
  "slug": "moving-check-dams-botanical-gardens-outdoor-assets-moisture"
}
