{
  "id": "blog-navigating-move-pastor",
  "title": "Navigating Your Move to Pastor: What Local Movers Want You to Know.",
  "titleAm": "",
  "excerpt": "Pastor area: landmarks, photos, IDs, one contact, neighbors, trucks, weather, Open First, quotes.",
  "excerptAm": "",
  "content": "<h2>Navigating your move to Pastor: what local movers want you to know</h2>\n<p>Local crews working the Pastor pocket—like many compact Addis neighborhoods—want clients to arrive with three things: accurate pins backed by landmarks, photos of the tightest turn, and gate rules submitted before the truck idles. “Pastor” on a map may not match what drivers call the block; ambiguity burns the first paid hour.</p>\n\n<h2>Confirm addresses with human landmarks</h2>\n<p>Text dispatch a nearby church, school, or known shop—even if apps show a correct dot. Drivers navigate by eyes and memory, not only GPS.</p>\n\n<h2>Photograph access before quote day</h2>\n<ul>\n<li>Gate width with reference scale.</li>\n<li>Steepest ramp or step run.</li>\n<li>Overhead branches that snag tall trucks.</li>\n</ul>\n\n<h2>IDs and compound spelling</h2>\n<p>Submit crew lists exactly as IDs read. Same-day edits fail on many portals; morning-of typos strand everyone.</p>\n\n<h2>One household voice to the lead</h2>\n<p>Assign a single adult for crew questions; another handles keys, kids, payments. Conflicting instructions slow loads and invite damage.</p>\n\n<h2>Neighbor notices and quiet hours</h2>\n<p>Post date, hours, contact. Tight communities reward courtesy; complaints steal elevator windows.</p>\n\n<h2>Truck class honesty</h2>\n<p>If only a mid truck reaches the gate, say so early. Shuttle pricing belongs in writing—not surprise at the narrow corner.</p>\n\n<h2>Weather mats and dust seasons</h2>\n<p>Lay cheap runners; seal mattress bags. Fine dust tracks into new paint jobs without drama.</p>\n\n<h2>Open First box discipline</h2>\n<p>Meds, chargers, tools, tea—off the truck, in the car. Night one without a kettle breeds bad decisions.</p>\n\n<h2>Three comparable quotes</h2>\n<p>Identical clips to each company. Normalize fuel, labor, materials, overtime, standby.</p>\n\n\n<h2>Kebele notice letter templates</h2>\n<p>Some blocks appreciate a simple signed notice on letterhead for large trucks. Ask your landlord; goodwill beats arguments at the horn.</p>\n\n<h2>Ride-hail pin drift</h2>\n<p>Confirm helper apps use the same gate your truck will use—split pins strand half your friends on the wrong corner.</p>\n\n\n<h2>Sunday processions and feast detours</h2>\n<p>Align truck arrival outside major liturgical peaks when streets compress. Buffers beat optimism.</p>\n\n<h2>Playground-adjacent moves</h2>\n<p>Assign a spotter when dollies cross sidewalks shared with children—safety slows minutes but prevents trauma.</p>\n\n<h2>Corner shops as landmark triangulation</h2><p>Send movers a photo of the shop sign at your turn—not only coordinates in chat apps that reorder pins.</p>\n\n<h2>Evening muezzin and move-out noise</h2><p>Plan hammering outside prayer windows when neighbors request—courtesy returns as borrowed dollies.</p>\n\n<h2>Street dog diplomacy</h2><p>Inform guards if territorial dogs patrol corners—crews coordinate timing, not fear.</p>\n\n<h2>Trash pickup days</h2><p>Ask neighbors which morning bins clear—first-week cardboard stacks grow fast after unpack.</p>\n\n<h2>Conclusion</h2>\n<p>Local movers want Pastor-bound clients to treat moving day like a joint operation: landmarks, photos, perfect paperwork, and calm communication. Deliver that, and the neighborhood opens its arms faster than the last box lands.</p>",
  "contentAm": "",
  "author": "Active Movers Team",
  "category": "moving-tips",
  "tags": [
    "Pastor",
    "Addis Ababa",
    "local movers",
    "relocation",
    "moving tips",
    "neighborhood"
  ],
  "tagsAm": [],
  "readTime": 58,
  "featuredImage": "https://www.activemoverset.com/images/gallary/qua37.jpeg",
  "images": [
    "https://www.activemoverset.com/images/gallary/qua38.jpeg",
    "https://www.activemoverset.com/images/gallary/qua39.jpeg"
  ],
  "status": "published",
  "publishedAt": "2027-05-14T10:30:00.000Z",
  "slug": "navigating-move-to-pastor-local-movers-want-you-to-know"
}