{
  "id": "professional-movers-vs-diy-addis",
  "title": "Why You Should Hire Professional Movers Instead of Doing It Yourself in Addis",
  "titleAmharic": "በአዲስ አበባ ውስጥ ራስዎ ሳይሆን ሙያዊ የመጓዝ አገልግሎት ለምን መቀበል እንዳለብዎት",
  "excerpt": "Discover why hiring professional movers in Addis Ababa is often more cost-effective and less stressful than DIY moving. Learn about hidden costs, time savings, and peace of mind.",
  "excerptAmharic": "በአዲስ አበባ ውስጥ ሙያዊ የመጓዝ አገልግሎት መቀበል ከራስዎ መጓዝ የበለጠ ምቹ እና ተጨማሪ ወጪ እንዳለው ይወቁ። የተደበቁ ወጪዎች፣ የጊዜ ቁጠባ እና የአእምሮ ሰላም ስለ ይማሩ።",
  "content": "<h2>Why You Should Hire Professional Movers Instead of Doing It Yourself in Addis</h2><p>Moving in Addis Ababa can be a challenging experience, especially when you consider the city's traffic, narrow streets, and unique urban landscape. While the idea of saving money by doing it yourself might seem appealing, hiring professional movers often proves to be the smarter choice. Here's why professional moving services in Addis Ababa are worth the investment.</p><h3>The Hidden Costs of DIY Moving in Addis Ababa</h3><h4>1. Transportation Costs</h4><p><strong>Renting a Vehicle:</strong></p><ul><li><strong>Small truck rental:</strong> 2,500-4,000 ETB per day</li><li><strong>Medium truck rental:</strong> 3,500-6,000 ETB per day</li><li><strong>Large truck rental:</strong> 5,000-8,000 ETB per day</li><li><strong>Insurance:</strong> 500-1,500 ETB per day</li><li><strong>Fuel costs:</strong> 1,500-3,000 ETB (depending on distance)</li><li><strong>Driver fees:</strong> 2,000-4,000 ETB per day (if you need a driver)</li></ul><p><strong>Total Transportation:</strong> 8,000-20,000 ETB</p><h4>2. Equipment and Supplies</h4><p><strong>Packing Materials:</strong></p><ul><li><strong>Cardboard boxes:</strong> 50-150 ETB each (need 20-50 boxes)</li><li><strong>Bubble wrap:</strong> 200-500 ETB per roll (need 3-5 rolls)</li><li><strong>Packing tape:</strong> 100-300 ETB per roll (need 5-10 rolls)</li><li><strong>Moving blankets:</strong> 1,000-2,000 ETB each (need 10-20)</li><li><strong>Plastic wrap:</strong> 300-600 ETB per roll (need 2-3 rolls)</li><li><strong>Labels and markers:</strong> 200-500 ETB</li><li><strong>Furniture pads:</strong> 500-1,000 ETB each (need 15-25)</li></ul><p><strong>Total Packing Supplies:</strong> 15,000-35,000 ETB</p><h4>3. Labor Costs</h4><p><strong>If You Hire Helpers:</strong></p><ul><li><strong>Loading crew:</strong> 1,500-3,000 ETB per person per day</li><li><strong>Unloading crew:</strong> 1,500-3,000 ETB per person per day</li><li><strong>Packing assistance:</strong> 2,000-4,000 ETB per person per day</li><li><strong>Furniture assembly:</strong> 1,000-2,500 ETB per person per day</li></ul><p><strong>Total Labor (4-6 people):</strong> 20,000-50,000 ETB</p><h4>4. Time and Opportunity Costs</h4><p><strong>Time Investment:</strong></p><ul><li><strong>Planning and research:</strong> 10-20 hours</li><li><strong>Packing:</strong> 20-40 hours</li><li><strong>Loading:</strong> 4-8 hours</li><li><strong>Transportation:</strong> 2-6 hours</li><li><strong>Unloading:</strong> 4-8 hours</li><li><strong>Unpacking:</strong> 15-30 hours</li><li><strong>Cleaning and setup:</strong> 10-20 hours</li></ul><p><strong>Total Time:</strong> 65-132 hours</p><p><strong>Opportunity Cost:</strong></p><ul><li><strong>Lost work time:</strong> 5,000-15,000 ETB per day</li><li><strong>Stress and fatigue:</strong> Immeasurable</li><li><strong>Risk of injury:</strong> Medical costs and lost productivity</li></ul><h3>Professional Moving Services: What You Get</h3><h4>1. Comprehensive Service Packages</h4><p><strong>Full-Service Moving (Recommended):</strong></p><ul><li><strong>Packing and unpacking:</strong> 15,000-30,000 ETB</li><li><strong>Loading and unloading:</strong> 8,000-15,000 ETB</li><li><strong>Transportation with insurance:</strong> 12,000-25,000 ETB</li><li><strong>Furniture disassembly/assembly:</strong> 5,000-12,000 ETB</li><li><strong>Cleaning services:</strong> 3,000-8,000 ETB</li><li><strong>Storage (if needed):</strong> 2,000-5,000 ETB per month</li></ul><p><strong>Total Full-Service:</strong> 45,000-95,000 ETB</p><p><strong>Basic Moving Service:</strong></p><ul><li><strong>Loading and unloading only:</strong> 8,000-15,000 ETB</li><li><strong>Transportation:</strong> 10,000-20,000 ETB</li><li><strong>Basic insurance:</strong> 2,000-5,000 ETB</li></ul><p><strong>Total Basic Service:</strong> 20,000-40,000 ETB</p><h4>2. Professional Equipment and Expertise</h4><p><strong>Specialized Equipment:</strong></p><ul><li><strong>Professional moving trucks:</strong> No rental costs</li><li><strong>Dollies and hand trucks:</strong> Included</li><li><strong>Furniture pads and blankets:</strong> Included</li><li><strong>Straps and tie-downs:</strong> Included</li><li><strong>Protective materials:</strong> Included</li></ul><p><strong>Expertise Benefits:</strong></p><ul><li><strong>Efficient packing techniques</strong></li><li><strong>Proper handling of fragile items</strong></li><li><strong>Space optimization</strong> in vehicles</li><li><strong>Safe lifting techniques</strong></li><li><strong>Damage prevention</strong> strategies</li></ul><h4>3. Insurance and Liability Coverage</h4><p><strong>Professional Insurance:</strong></p><ul><li><strong>Full value protection:</strong> 2,000-5,000 ETB</li><li><strong>Basic coverage:</strong> 1,000-3,000 ETB</li><li><strong>Liability insurance:</strong> Included</li><li><strong>Worker's compensation:</strong> Included</li></ul><p><strong>DIY Insurance Risks:</strong></p><ul><li><strong>No coverage</strong> for damaged items</li><li><strong>Personal liability</strong> for injuries</li><li><strong>Vehicle damage</strong> responsibility</li><li><strong>Property damage</strong> liability</li></ul><h3>Addis Ababa-Specific Challenges</h3><h4>1. Traffic and Navigation</h4><p><strong>Professional Advantages:</strong></p><ul><li><strong>Local knowledge</strong> of best routes</li><li><strong>Traffic pattern awareness</strong></li><li><strong>Parking solutions</strong> for loading/unloading</li><li><strong>Permit knowledge</strong> for restricted areas</li><li><strong>Time optimization</strong> for busy periods</li></ul><p><strong>DIY Challenges:</strong></p><ul><li><strong>Getting lost</strong> in unfamiliar areas</li><li><strong>Traffic delays</strong> and stress</li><li><strong>Parking difficulties</strong></li><li><strong>Route planning</strong> complexity</li><li><strong>Time wastage</strong> due to inexperience</li></ul><h4>2. Building and Access Issues</h4><p><strong>Common Problems in Addis:</strong></p><ul><li><strong>Narrow staircases</strong> in older buildings</li><li><strong>Limited elevator access</strong></li><li><strong>Restricted parking</strong> areas</li><li><strong>Security requirements</strong> in compounds</li><li><strong>Building regulations</strong> and permits</li></ul><p><strong>Professional Solutions:</strong></p><ul><li><strong>Specialized equipment</strong> for tight spaces</li><li><strong>Building access</strong> relationships</li><li><strong>Permit handling</strong> expertise</li><li><strong>Security coordination</strong></li><li><strong>Alternative access</strong> methods</li></ul><h4>3. Weather and Seasonal Considerations</h4><p><strong>Rainy Season Challenges (June-September):</strong></p><ul><li><strong>Wet roads</strong> and slippery conditions</li><li><strong>Mud and dirt</strong> on belongings</li><li><strong>Delayed schedules</strong> due to weather</li><li><strong>Protection needs</strong> for outdoor items</li></ul><p><strong>Professional Weather Management:</strong></p><ul><li><strong>Weather monitoring</strong> and planning</li><li><strong>Protective equipment</strong> and materials</li><li><strong>Flexible scheduling</strong> options</li><li><strong>Indoor alternatives</strong> for loading</li></ul><h3>Cost Comparison: DIY vs Professional</h3><h4>1. Complete Cost Breakdown</h4><p><strong>DIY Moving Total Costs:</strong></p><ul><li><strong>Transportation:</strong> 8,000-20,000 ETB</li><li><strong>Packing supplies:</strong> 15,000-35,000 ETB</li><li><strong>Labor (if hired):</strong> 20,000-50,000 ETB</li><li><strong>Insurance:</strong> 0-5,000 ETB</li><li><strong>Time cost:</strong> 10,000-30,000 ETB</li><li><strong>Potential damages:</strong> 5,000-20,000 ETB</li><li><strong>Stress and health:</strong> Immeasurable</li></ul><p><strong>Total DIY:</strong> 58,000-160,000 ETB</p><p><strong>Professional Moving Total Costs:</strong></p><ul><li><strong>Full-service package:</strong> 45,000-95,000 ETB</li><li><strong>Additional services:</strong> 5,000-15,000 ETB</li><li><strong>Tips and extras:</strong> 2,000-5,000 ETB</li><li><strong>Time saved:</strong> 0 ETB (actually saves money)</li><li><strong>Peace of mind:</strong> Priceless</li></ul><p><strong>Total Professional:</strong> 52,000-115,000 ETB</p><h4>2. Hidden Savings with Professionals</h4><p><strong>Time Savings:</strong></p><ul><li><strong>65-132 hours</strong> of your time</li><li><strong>Opportunity cost</strong> of lost work</li><li><strong>Stress reduction</strong> and better health</li><li><strong>Faster completion</strong> of move</li></ul><p><strong>Damage Prevention:</strong></p><ul><li><strong>Professional handling</strong> reduces breakage</li><li><strong>Proper packing</strong> prevents damage</li><li><strong>Insurance coverage</strong> for accidents</li><li><strong>Expertise</strong> in fragile items</li></ul><p><strong>Efficiency Benefits:</strong></p><ul><li><strong>Faster loading/unloading</strong></li><li><strong>Better space utilization</strong></li><li><strong>Optimized routes</strong> and timing</li><li><strong>Reduced physical strain</strong></li></ul><h3>Quality of Service Comparison</h3><h4>1. Professional Service Standards</h4><p><strong>Trained Personnel:</strong></p><ul><li><strong>Background checks</strong> and screening</li><li><strong>Professional training</strong> in moving techniques</li><li><strong>Customer service</strong> skills</li><li><strong>Problem-solving</strong> abilities</li><li><strong>Reliability</strong> and punctuality</li></ul><p><strong>Service Guarantees:</strong></p><ul><li><strong>On-time delivery</strong> promises</li><li><strong>Damage protection</strong> policies</li><li><strong>Satisfaction guarantees</strong></li><li><strong>Follow-up services</strong></li><li><strong>Complaint resolution</strong> processes</li></ul><h4>2. DIY Service Quality</h4><p><strong>Potential Issues:</strong></p><ul><li><strong>Inconsistent quality</strong> of helpers</li><li><strong>No guarantees</strong> or warranties</li><li><strong>Limited expertise</strong> in handling</li><li><strong>Unreliable availability</strong></li><li><strong>No accountability</strong> for problems</li></ul><p><strong>Risk Factors:</strong></p><ul><li><strong>Personal injury</strong> risks</li><li><strong>Property damage</strong> liability</li><li><strong>Incomplete services</strong></li><li><strong>No backup</strong> if problems arise</li><li><strong>Stress and fatigue</strong></li></ul><h3>Specialized Services Only Professionals Provide</h3><h4>1. Fragile and Valuable Items</h4><p><strong>Professional Handling:</strong></p><ul><li><strong>Specialized packing</strong> materials</li><li><strong>Custom crating</strong> services (5,000-15,000 ETB)</li><li><strong>Climate-controlled</strong> transportation</li><li><strong>White-glove service</strong> (10,000-25,000 ETB)</li><li><strong>Insurance coverage</strong> for valuables</li></ul><p><strong>DIY Limitations:</strong></p><ul><li><strong>Limited expertise</strong> in fragile items</li><li><strong>No specialized</strong> equipment</li><li><strong>Higher risk</strong> of damage</li><li><strong>No insurance</strong> coverage</li><li><strong>Stress and worry</strong></li></ul><h4>2. Large and Heavy Items</h4><p><strong>Professional Capabilities:</strong></p><ul><li><strong>Specialized equipment</strong> (hoists, dollies)</li><li><strong>Team coordination</strong> for heavy items</li><li><strong>Safety protocols</strong> and training</li><li><strong>Damage prevention</strong> techniques</li><li><strong>Proper lifting</strong> methods</li></ul><p><strong>DIY Challenges:</strong></p><ul><li><strong>Physical limitations</strong></li><li><strong>Safety risks</strong></li><li><strong>Equipment limitations</strong></li><li><strong>Coordination difficulties</strong></li><li><strong>Potential injuries</strong></li></ul><h4>3. Storage and Logistics</h4><p><strong>Professional Storage:</strong></p><ul><li><strong>Climate-controlled</strong> facilities</li><li><strong>Security systems</strong> and monitoring</li><li><strong>Inventory management</strong></li><li><strong>Flexible access</strong> options</li><li><strong>Insurance coverage</strong></li></ul><p><strong>Cost:</strong> 2,000-5,000 ETB per month</p><h3>When DIY Might Make Sense</h3><h4>1. Limited Scope Moves</h4><p><strong>Suitable for DIY:</strong></p><ul><li><strong>Studio apartment</strong> (1-2 rooms)</li><li><strong>Minimal furniture</strong></li><li><strong>Short distance</strong> (within same area)</li><li><strong>Flexible timeline</strong></li><li><strong>Strong support</strong> network</li></ul><p><strong>Cost Threshold:</strong> Under 30,000 ETB total value</p><h4>2. Budget Constraints</h4><p><strong>If Professional Moving is Not Affordable:</strong></p><ul><li><strong>Consider basic</strong> moving services only</li><li><strong>Partial services</strong> (loading/unloading only)</li><li><strong>Shared moving</strong> with neighbors</li><li><strong>Staged moving</strong> over time</li><li><strong>Community support</strong> networks</li></ul><h4>3. Simple Moves</h4><p><strong>DIY-Friendly Scenarios:</strong></p><ul><li><strong>Student housing</strong></li><li><strong>Temporary accommodation</strong></li><li><strong>Minimal belongings</strong></li><li><strong>Local moves</strong> within neighborhood</li><li><strong>Emergency situations</strong></li></ul><h3>Making the Right Choice</h3><h4>1. Assessment Questions</h4><p><strong>Ask Yourself:</strong></p><ul><li><strong>How much time</strong> can you dedicate?</li><li><strong>What's your physical</strong> capability?</li><li><strong>Do you have reliable</strong> help available?</li><li><strong>What's the value</strong> of your belongings?</li><li><strong>How important</strong> is your time?</li><li><strong>Can you handle</strong> stress and complications?</li></ul><h4>2. Professional Moving Recommendations</h4><p><strong>Choose Professional When:</strong></p><ul><li><strong>Moving valuable</strong> items</li><li><strong>Limited time</strong> available</li><li><strong>Physical limitations</strong> exist</li><li><strong>Long distance</strong> move</li><li><strong>Complex logistics</strong> involved</li><li><strong>Peace of mind</strong> is important</li></ul><h4>3. Hybrid Approach</h4><p><strong>Partial Professional Services:</strong></p><ul><li><strong>Packing only:</strong> 15,000-30,000 ETB</li><li><strong>Loading/unloading only:</strong> 8,000-15,000 ETB</li><li><strong>Transportation only:</strong> 10,000-20,000 ETB</li><li><strong>Unpacking only:</strong> 10,000-20,000 ETB</li></ul><p><strong>DIY Components:</strong></p><ul><li><strong>Self-packing</strong> of non-fragile items</li><li><strong>Self-transportation</strong> for small items</li><li><strong>Self-unpacking</strong> and organization</li><li><strong>Self-cleaning</strong> and setup</li></ul><h3>Choosing the Right Moving Company</h3><h4>1. Research and Comparison</h4><p><strong>Company Evaluation:</strong></p><ul><li><strong>Licensed and insured</strong></li><li><strong>Local experience</strong> in Addis Ababa</li><li><strong>Positive reviews</strong> and references</li><li><strong>Transparent pricing</strong></li><li><strong>Professional staff</strong></li></ul><p><strong>Get Multiple Quotes:</strong></p><ul><li><strong>At least 3 estimates</strong></li><li><strong>Detailed breakdowns</strong></li><li><strong>Compare services</strong> included</li><li><strong>Check for hidden</strong> costs</li><li><strong>Verify insurance</strong> coverage</li></ul><h4>2. Questions to Ask</h4><p><strong>Essential Questions:</strong></p><ul><li><strong>What's included</strong> in the price?</li><li><strong>What's the insurance</strong> coverage?</li><li><strong>How do you handle</strong> fragile items?</li><li><strong>What's your cancellation</strong> policy?</li><li><strong>Do you provide</strong> packing materials?</li><li><strong>What's your timeline</strong> for completion?</li></ul><h4>3. Red Flags to Avoid</h4><p><strong>Warning Signs:</strong></p><ul><li><strong>Unusually low</strong> prices</li><li><strong>No written</strong> contracts</li><li><strong>No insurance</strong> coverage</li><li><strong>Unprofessional</strong> behavior</li><li><strong>No local</strong> references</li><li><strong>Pressure tactics</strong></li></ul><h3>Conclusion</h3><p>While DIY moving might seem like a way to save money, the hidden costs, time investment, and stress often make professional moving services the better choice in Addis Ababa. Professional movers bring expertise, equipment, insurance, and peace of mind that DIY moving simply cannot provide.</p><p><strong>Key Takeaways:</strong></p><ul><li><strong>Professional moving</strong> is often more cost-effective</li><li><strong>Time savings</strong> are significant</li><li><strong>Reduced stress</strong> and physical strain</li><li><strong>Better protection</strong> for your belongings</li><li><strong>Expertise</strong> in handling challenges</li><li><strong>Insurance coverage</strong> and guarantees</li></ul><p><strong>Final Recommendation:</strong></p><p>Unless you have a very simple move with minimal belongings and plenty of time, professional moving services in Addis Ababa are worth the investment. The peace of mind, time savings, and reduced risk of damage make professional movers the smart choice for most relocations.</p><p><strong>Next Steps:</strong></p><ol><li><strong>Get quotes</strong> from 3-4 reputable companies</li><li><strong>Compare services</strong> and pricing</li><li><strong>Check references</strong> and reviews</li><li><strong>Ask questions</strong> about insurance and guarantees</li><li><strong>Book early</strong> to secure your preferred date</li><li><strong>Prepare your belongings</strong> for professional packing</li></ol><p>Remember: A successful move is an investment in your new beginning. Choose the option that gives you the best value for your money, time, and peace of mind.</p>",
  "contentAmharic": "<h2>በአዲስ አበባ ውስጥ ራስዎ ሳይሆን ሙያዊ የመጓዝ አገልግሎት ለምን መቀበል እንዳለብዎት</h2><p>በአዲስ አበባ ውስጥ መጓዝ ተገራሚ ልምድ ሊሆን ይችላል፣ በተለይም የከተማውን ትራፊክ፣ ጠባብ መንገዶች እና ልዩ የከተማ መሬት ከግምት ውስጥ በማስገባት። በራስዎ ገንዘብ በመቆጠብ የራስዎ መጓዝ ሀሳብ የሚስብ ሊሆን ቢሆንም፣ ሙያዊ የመጓዝ አገልግሎት መቀበል ብዙውን ጊዜ የበለጠ ዘመናዊ ምርጫ እንደሆነ ያረጋግጣል። ሙያዊ የመጓዝ አገልግሎቶች በአዲስ አበባ ውስጥ የመዋዕለ ንብረት ለምን እንደሆኑ እነሆ።</p>",
  "featuredImage": "https://www.activemoverset.com/images/professional-movers-addis.jpg",
  "images": [
    "https://www.activemoverset.com/images/diy-moving-challenges.jpg",
    "https://www.activemoverset.com/images/professional-moving-team.jpg",
    "https://www.activemoverset.com/images/moving-equipment.jpg",
    "https://www.activemoverset.com/images/addis-traffic-moving.jpg",
    "https://www.activemoverset.com/images/moving-insurance.jpg"
  ],
  "tags": [
    "professional movers",
    "diy moving",
    "addis ababa",
    "moving costs",
    "moving services",
    "moving comparison",
    "moving tips",
    "relocation",
    "moving planning",
    "moving insurance"
  ],
  "category": "moving-tips",
  "author": "Active Movers Team",
  "publishedAt": "2025-10-08T16:25:00.000Z",
  "updatedAt": "2025-10-08T16:25:00.000Z",
  "readTime": "20-25 minutes",
  "status": "published",
  "slug": "professional-movers-vs-diy-addis",
  "seo": {
    "title": "Why Hire Professional Movers vs DIY Moving in Addis Ababa | Cost Comparison 2025",
    "description": "Discover why professional movers in Addis Ababa are often more cost-effective than DIY moving. Compare costs, benefits, and hidden expenses of self-moving vs professional services.",
    "keywords": [
      "professional movers addis ababa",
      "diy moving vs professional",
      "moving costs addis ababa",
      "moving services ethiopia",
      "moving comparison",
      "moving tips addis",
      "relocation services",
      "moving planning",
      "moving insurance",
      "moving equipment"
    ],
    "canonicalUrl": "https://www.activemoverset.com/blog/professional-movers-vs-diy-addis"
  },
  "relatedPosts": [
    "affordable-movers-addis-ababa",
    "essential-moving-tips-addis-ababa",
    "step-by-step-moving-checklist-addis-ababa",
    "long-distance-move-addis-ethiopian-cities"
  ],
  "schema": {
    "@context": "https://schema.org",
    "@type": "Article",
    "headline": "Why You Should Hire Professional Movers Instead of Doing It Yourself in Addis",
    "description": "Discover why hiring professional movers in Addis Ababa is often more cost-effective and less stressful than DIY moving. Learn about hidden costs, time savings, and peace of mind.",
    "author": {
      "@type": "Organization",
      "name": "Active Movers & Packers",
      "url": "https://www.activemoverset.com"
    },
    "publisher": {
      "@type": "Organization",
      "name": "Active Movers & Packers",
      "url": "https://www.activemoverset.com",
      "logo": {
        "@type": "ImageObject",
        "url": "https://www.activemoverset.com/images/logo.jpg"
      }
    },
    "datePublished": "2024-01-15T10:00:00.000Z",
    "dateModified": "2024-01-15T10:00:00.000Z",
    "mainEntityOfPage": {
      "@type": "WebPage",
      "@id": "https://www.activemoverset.com/blog/professional-movers-vs-diy-addis"
    },
    "image": [
      "https://www.activemoverset.com/images/professional-movers-addis.jpg",
      "https://www.activemoverset.com/images/diy-moving-challenges.jpg",
      "https://www.activemoverset.com/images/professional-moving-team.jpg"
    ],
    "articleSection": "Moving Guides",
    "wordCount": 7500,
    "inLanguage": "en"
  }
}
