{
  "id": "blog-top-movers-old-airport",
  "title": "Top Movers in Old Airport Area: Affordable Moving Solutions",
  "titleAm": "",
  "excerpt": "Old Airport area: what drives moving costs, ethical ways to save, reading estimates, school traffic, payments, insurance, and when cheap bids are traps.",
  "excerptAm": "",
  "content": "<h2>Old Airport area: affordable moving without nasty surprises</h2><p>The Old Airport neighborhood blends residential compounds, schools, and services left from the city's aviation history. Demand for movers is steady, and price bands vary widely. Affordable solutions exist—but affordability should mean transparent scope and fair labor rates, not hidden fees that appear when the truck is full.</p><p>This article shows how to lower cost ethically, read quotes line by line, and spot when a cheap bid is actually expensive.</p><h2>What drives price in Old Airport moves</h2><h3>Carry distance and parking</h3><p>If the truck parks legally fifty meters away, every sofa trip adds minutes. Photograph the path and share it when requesting estimates.</p><h3>Volume and truck fit</h3><p>One full truck beats two shuttles when shuttle labor multiplies hours. Declutter before quote day to possibly drop a truck class.</p><h3>Service tier</h3><p>Owner-packed boxes save money if packing quality is strong. Hybrid models—pros pack kitchen and glass, you pack clothes—balance savings and safety.</p><h2>Ethical cost cuts</h2><ul><li>Move mid-month Tuesday–Thursday when crews have slack.</li><li>Stage sealed boxes near the loading door if rules allow.</li><li>Use small boxes for books; reinforce bottoms.</li><li>Bundle disposal or donation hauls with the same vendor.</li></ul><h2>Reading an estimate like a project manager</h2><p>Demand labor hours or flat fee basis, truck size, fuel policy, materials per unit, stair assumptions, overtime rate, and cancellation terms. If a line says TBD, ask when it becomes a number.</p><h2>School traffic and quiet hours</h2><p>Old Airport routes spike at school drop-off and pickup. Align truck arrival outside those peaks when possible. Ask management about noise rules for hammering or drilling.</p><h2>Older buildings and maintenance</h2><p>Uneven stairs and worn railings need slower pacing, not cheaper crews. Saving money on inexperienced labor often costs more in wall repairs.</p><h2>Payment sanity</h2><p>Small deposit to hold date, balance after successful unload is standard. Full prepayment is a red flag unless trust is exceptional and documented.</p><h2>When the low bid is a trap</h2><ul><li>No written scope.</li><li>Refuses to visit or video survey.</li><li>Cannot name supervisor or crew count.</li><li>Pressure to decide in one phone call.</li></ul><h2>Insurance and liability</h2><p>Ask liability caps and exclusions. Photograph scratches on furniture before the move. High-value items may need extra coverage.</p><h2>Family and roommate splits</h2><p>Shared flats should label boxes with initials. One person speaks to the crew lead to avoid conflicting instructions.</p><h2>Post-move budget</h2><p>Hold roughly ten percent contingency for cleaning, small hardware, or extra hangers. Affordable plans still hit snags.</p><h2>Shared rides and borrowed hands</h2><p>Friends helping should not direct the professional crew. Assign friends to childcare, snacks, or perimeter watch. Conflicting instructions cost billable hours.</p><h2>Secondhand furniture flips</h2><p>If you buy used pieces arriving on move day, photograph them before the truck loads your existing goods—insurance baselines blur when multiple sources mix.</p><h2>Internet and utility appointment stacking</h2><p>Book installs after the heaviest furniture is placed so technicians are not trapped behind wardrobes.</p><h2>Noise windows and drill curfews</h2><p>Ask management when power tools are allowed. Fines for after-hours noise erase moving savings fast.</p><h2>Seasonal demand spikes</h2><p>End-of-month turnover and pre-holiday weeks compress crew availability. If you must move then, book earlier and widen your date window one day on each side for pricing leverage.</p><h2>Box quality that saves money</h2><p>Double-tape bottoms on book boxes. Weak cardboard explodes in corridors, creating rescue labor you pay for. Free boxes are fine for linens; buy new for dishes.</p><h2>Long-carry time math</h2><p>Ask estimators how many minutes per round trip they assumed from truck to door. Multiply by box count mentally—if it feels low, the quote is optimistic.</p><h2>Donation and disposal routing</h2><p>Movers who partner with charities may charge a fair haul fee but save you separate truck rentals. Get disposal in writing with weight or item limits.</p><h2>Conclusion</h2><p>Top movers in the Old Airport area earn the affordable label through clear quotes, efficient scheduling, and right-sized trucks—not through cutting corners you will pay for later. Compare apples to apples, then commit.</p>",
  "contentAm": "",
  "author": "Active Movers Team",
  "category": "moving-tips",
  "tags": [
    "Old Airport",
    "Addis Ababa",
    "affordable movers",
    "moving costs",
    "budget move",
    "relocation"
  ],
  "tagsAm": [],
  "readTime": 34,
  "featuredImage": "https://www.activemoverset.com/images/gallary/qua4.jpeg",
  "images": [
    "https://www.activemoverset.com/images/gallary/qua5.jpeg",
    "https://www.activemoverset.com/images/gallary/qua6.jpeg"
  ],
  "status": "published",
  "publishedAt": "2026-02-20T11:00:00.000Z",
  "slug": "top-movers-old-airport-affordable-moving-solutions"
}